ttc/TremTecCLI.py
ttc/__init__.py
ttc/main.py
ttc-0.0.0.dist-info/METADATA
ttc-0.0.0.dist-info/WHEEL
ttc-0.0.0.dist-info/entry_points.txt
ttc-0.0.0.dist-info/top_level.txt
ttc-0.0.0.dist-info/RECORD
