Metadata-Version: 2.1
Name: ttc
Version: 0.0.0
Summary: TremTec CLI utilities
Home-page: https://gitlab.com/tremtec/ttc
Author: TremTec Org.
Author-email: marco@tremtec.com
License: UNKNOWN
Keywords: tremtec cli
Platform: UNKNOWN
Classifier: Development Status :: 3 - Alpha
Classifier: Intended Audience :: Developers
Classifier: Topic :: Software Development :: Build Tools
Classifier: License :: OSI Approved :: MIT License
Classifier: Programming Language :: Python :: 3
Classifier: Programming Language :: Python :: 3.4
Classifier: Programming Language :: Python :: 3.5
Classifier: Programming Language :: Python :: 3.6
Requires-Dist: click
Requires-Dist: click-completion
Requires-Dist: PyInquirer
Provides-Extra: dev
Requires-Dist: flake8 ; extra == 'dev'
Requires-Dist: black ; extra == 'dev'
Requires-Dist: pylint ; extra == 'dev'
Requires-Dist: pydocstyle ; extra == 'dev'
Requires-Dist: pycodestyle ; extra == 'dev'
Requires-Dist: rope ; extra == 'dev'
Provides-Extra: test
Requires-Dist: coverage ; extra == 'test'
